cttilemap/__init__.py
cttilemap/classes.py
cttilemap/errors.py
cttilemap-1.0.0.dist-info/LICENSE
cttilemap-1.0.0.dist-info/METADATA
cttilemap-1.0.0.dist-info/WHEEL
cttilemap-1.0.0.dist-info/top_level.txt
cttilemap-1.0.0.dist-info/RECORD
