Metadata-Version: 2.1
Name: cttilemap
Version: 1.0.0
Summary: A pure-python library to parse Clickteam TileMap files.
Author-email: baltdev <heptor42@gmail.com>
Project-URL: Homepage, https://github.com/balt-dev/clickteam-tilemap-py
Project-URL: Bug Tracker, https://github.com/balt-dev/clickteam-tilemap-py/issues
Classifier: Programming Language :: Python :: 3
Classifier: License :: OSI Approved :: MIT License
Classifier: Operating System :: OS Independent
Requires-Python: >=3.10
License-File: LICENSE
Requires-Dist: attrs
